cyberplant_Scrapy-1.2.0.dev2.dist-info/DESCRIPTION.rst
cyberplant_Scrapy-1.2.0.dev2.dist-info/METADATA
cyberplant_Scrapy-1.2.0.dev2.dist-info/RECORD
cyberplant_Scrapy-1.2.0.dev2.dist-info/WHEEL
cyberplant_Scrapy-1.2.0.dev2.dist-info/entry_points.txt
cyberplant_Scrapy-1.2.0.dev2.dist-info/metadata.json
cyberplant_Scrapy-1.2.0.dev2.dist-info/top_level.txt
scrapy/VERSION
scrapy/__init__.py
scrapy/_monkeypatches.py
scrapy/cmdline.py
scrapy/command.py
scrapy/conf.py
scrapy/crawler.py
scrapy/dupefilter.py
scrapy/dupefilters.py
scrapy/exceptions.py
scrapy/exporters.py
scrapy/extension.py
scrapy/interfaces.py
scrapy/item.py
scrapy/link.py
scrapy/linkextractor.py
scrapy/log.py
scrapy/logformatter.py
scrapy/mail.py
scrapy/middleware.py
scrapy/mime.types
scrapy/project.py
scrapy/resolver.py
scrapy/responsetypes.py
scrapy/shell.py
scrapy/signalmanager.py
scrapy/signals.py
scrapy/spider.py
scrapy/spiderloader.py
scrapy/spidermanager.py
scrapy/squeue.py
scrapy/squeues.py
scrapy/stats.py
scrapy/statscol.py
scrapy/statscollectors.py
scrapy/telnet.py
scrapy/commands/__init__.py
scrapy/commands/bench.py
scrapy/commands/check.py
scrapy/commands/crawl.py
scrapy/commands/edit.py
scrapy/commands/fetch.py
scrapy/commands/genspider.py
scrapy/commands/list.py
scrapy/commands/parse.py
scrapy/commands/runspider.py
scrapy/commands/settings.py
scrapy/commands/shell.py
scrapy/commands/startproject.py
scrapy/commands/version.py
scrapy/commands/view.py
scrapy/contracts/__init__.py
scrapy/contracts/default.py
scrapy/contrib/__init__.py
scrapy/contrib/closespider.py
scrapy/contrib/corestats.py
scrapy/contrib/debug.py
scrapy/contrib/feedexport.py
scrapy/contrib/httpcache.py
scrapy/contrib/logstats.py
scrapy/contrib/memdebug.py
scrapy/contrib/memusage.py
scrapy/contrib/spiderstate.py
scrapy/contrib/statsmailer.py
scrapy/contrib/throttle.py
scrapy/contrib/downloadermiddleware/__init__.py
scrapy/contrib/downloadermiddleware/ajaxcrawl.py
scrapy/contrib/downloadermiddleware/chunked.py
scrapy/contrib/downloadermiddleware/cookies.py
scrapy/contrib/downloadermiddleware/decompression.py
scrapy/contrib/downloadermiddleware/defaultheaders.py
scrapy/contrib/downloadermiddleware/downloadtimeout.py
scrapy/contrib/downloadermiddleware/httpauth.py
