Metadata-Version: 2.0
Name: cyberplant-Scrapy
Version: 1.2.0.dev2
Summary: A high-level Web Crawling and Web Scraping framework
Home-page: http://scrapy.org
Author: Pablo Hoffman
Author-email: pablo@pablohoffman.com
License: BSD
Platform: UNKNOWN
Classifier: Framework :: Scrapy
Classifier: Development Status :: 5 - Production/Stable
Classifier: Environment :: Console
Classifier: Intended Audience :: Developers
Classifier: License :: OSI Approved :: BSD License
Classifier: Operating System :: OS Independent
Classifier: Programming Language :: Python
Classifier: Programming Language :: Python :: 2
Classifier: Programming Language :: Python :: 2.7
Classifier: Programming Language :: Python :: 3
Classifier: Programming Language :: Python :: 3.3
Classifier: Programming Language :: Python :: 3.4
Classifier: Programming Language :: Python :: 3.5
Classifier: Topic :: Internet :: WWW/HTTP
Classifier: Topic :: Software Development :: Libraries :: Application Frameworks
Classifier: Topic :: Software Development :: Libraries :: Python Modules
Requires-Dist: PyDispatcher (>=2.0.5)
Requires-Dist: Twisted (>=10.0.0)
Requires-Dist: cssselect (>=0.9)
Requires-Dist: lxml
Requires-Dist: parsel (>=0.9.3)
Requires-Dist: pyOpenSSL
Requires-Dist: queuelib
Requires-Dist: service-identity
Requires-Dist: six (>=1.5.2)
Requires-Dist: w3lib (>=1.14.2)
